ai_terminal/__init__.py
ai_terminal/agent.py
ai_terminal/agent_graph.py
ai_terminal/animations.py
ai_terminal/cli.py
ai_terminal/config.py
ai_terminal/conversation_history.py
ai_terminal/file_monitor.py
ai_terminal/license.py
ai_terminal/llm.py
ai_terminal/notifications.py
ai_terminal/persistence.py
ai_terminal/progress.py
ai_terminal/safety.py
ai_terminal/testing.py
ai_terminal/text_formatter.py
ai_terminal/themes.py
ai_terminal/tools.py
ai_terminal/utils.py
ai_terminal/vector_store.py
flawhunt-1.0.8.dist-info/licenses/LICENSE.md
flawhunt-1.0.8.dist-info/METADATA
flawhunt-1.0.8.dist-info/WHEEL
flawhunt-1.0.8.dist-info/entry_points.txt
flawhunt-1.0.8.dist-info/top_level.txt
flawhunt-1.0.8.dist-info/RECORD
