Metadata-Version: 2.4
Name: flawhunt
Version: 1.0.8
Summary: Natural language to shell with explanations & confirmations
Home-page: https://github.com/gamkers/GAMKERS_CLI.git
Author: GAMKERS
Author-email: gamkers@example.com
Classifier: Development Status :: 4 - Beta
Classifier: Intended Audience :: Developers
Classifier: License :: OSI Approved :: MIT License
Classifier: Operating System :: OS Independent
Classifier: Programming Language :: Python :: 3
Classifier: Programming Language :: Python :: 3.8
Classifier: Programming Language :: Python :: 3.9
Classifier: Programming Language :: Python :: 3.10
Classifier: Programming Language :: Python :: 3.11
Classifier: Programming Language :: Python :: 3.12
Classifier: Programming Language :: Python :: 3.13
Requires-Python: >=3.8
License-File: LICENSE.md
Requires-Dist: google-generativeai>=0.3.0
Requires-Dist: langchain>=0.3.0
Requires-Dist: langchain-google-genai>=2.0.0
Requires-Dist: langchain-groq>=0.1.0
Requires-Dist: prompt-toolkit>=3.0.0
Requires-Dist: typer>=0.9.0
Requires-Dist: rich>=13.0.0
Requires-Dist: faiss-cpu>=1.7.0
Requires-Dist: sentence-transformers>=2.2.0
Requires-Dist: requests>=2.28.0
Requires-Dist: beautifulsoup4>=4.11.0
Requires-Dist: pycryptodome>=3.15.0
Requires-Dist: cryptography>=3.4.0
Requires-Dist: supabase>=2.0.0
Requires-Dist: watchdog>=4.0.0
Requires-Dist: langgraph>=0.0.10
Dynamic: author
Dynamic: author-email
Dynamic: classifier
Dynamic: description
Dynamic: description-content-type
Dynamic: home-page
Dynamic: license-file
Dynamic: requires-dist
Dynamic: requires-python
Dynamic: summary
